MongodbDuplicateChecker/__init__.py
MongodbDuplicateChecker/delete_duplicate.py
mongochecker-0.0.2.dist-info/LICENSE
mongochecker-0.0.2.dist-info/METADATA
mongochecker-0.0.2.dist-info/WHEEL
mongochecker-0.0.2.dist-info/entry_points.txt
mongochecker-0.0.2.dist-info/top_level.txt
mongochecker-0.0.2.dist-info/RECORD
