Metadata-Version: 2.1
Name: mongochecker
Version: 0.0.2
Summary: a tool to remove mongodb duplicate data or copy mongodb data
Home-page: https://github.com/ga1008/mongochecker
Author: Guardian
Author-email: zhling2012@live.com
Maintainer: Guardian
Maintainer-email: zhling2012@live.com
License: UNKNOWN
Platform: UNKNOWN
Classifier: Programming Language :: Python :: 3
Classifier: License :: OSI Approved :: MIT License
Classifier: Operating System :: OS Independent
Requires-Dist: tqdm
Requires-Dist: pymongo
